{
  "label": "弁護士",
  "problems": [
    {"type": "離婚・家族問題", "detail": "離婚を考えているが財産分与や親権のことが不安"},
    {"type": "債務整理・自己破産", "detail": "借金が増えすぎて返せなくなってきた"},
    {"type": "交通事故", "detail": "事故に遭い保険会社の示談額が適正かどうかわからない"},
    {"type": "相続トラブル", "detail": "兄弟間で遺産相続でもめていて解決したい"},
    {"type": "労働問題", "detail": "不当解雇・残業代未払いで会社と争いたい"},
    {"type": "詐欺・消費者被害", "detail": "詐欺にあいお金を取り返したい"}
  ],
  "age_range": [25, 75],
  "age_weights": {
    "25-40": 0.25,
    "41-60": 0.50,
    "61-75": 0.25
  },
  "gender_ratio": {"男性": 0.50, "女性": 0.50},
  "it_literacy": ["低い（電話・対面が好き）", "普通（ネット検索はする）", "高い（LINEやZoomでの相談希望）"],
  "it_weights": [0.35, 0.45, 0.20],
  "price_sensitivity": ["かなり敏感（費用が高くて相談をためらっている）", "普通（成功報酬なら払える）", "あまり気にしない（早く解決できるなら）"],
  "price_weights": [0.45, 0.35, 0.20],
  "urgency": ["高い（今すぐ相談したい・期限がある）", "中程度（近いうちに動きたい）", "低い（まず情報収集したい）"],
  "urgency_weights": [0.40, 0.35, 0.25],
  "trust_factors": [
    "初回相談が無料かどうかが重要",
    "専門分野（離婚・借金など）の実績が豊富",
    "費用の目安を事前に教えてもらえる",
    "相談しやすい雰囲気・親しみやすさ",
    "近所や地元の弁護士を探している"
  ]
}
